rethinkdb/__init__.py
rethinkdb/__main__.py
rethinkdb/_dump.py
rethinkdb/_export.py
rethinkdb/_import.py
rethinkdb/_index_rebuild.py
rethinkdb/_restore.py
rethinkdb/ast.py
rethinkdb/docs.py
rethinkdb/errors.py
rethinkdb/handshake.py
rethinkdb/helpers.py
rethinkdb/logger.py
rethinkdb/net.py
rethinkdb/ql2_pb2.py
rethinkdb/query.py
rethinkdb/utils_common.py
rethinkdb/version.py
rethinkdb/asyncio_net/__init__.py
rethinkdb/asyncio_net/net_asyncio.py
rethinkdb/backports/__init__.py
rethinkdb/backports/ssl_match_hostname/LICENSE.txt
rethinkdb/backports/ssl_match_hostname/README.txt
rethinkdb/backports/ssl_match_hostname/__init__.py
rethinkdb/gevent_net/__init__.py
rethinkdb/gevent_net/net_gevent.py
rethinkdb/tornado_net/__init__.py
rethinkdb/tornado_net/net_tornado.py
rethinkdb/trio_net/__init__.py
rethinkdb/trio_net/net_trio.py
rethinkdb/twisted_net/__init__.py
rethinkdb/twisted_net/net_twisted.py
rethinkdb-2.4.9.dist-info/LICENSE
rethinkdb-2.4.9.dist-info/METADATA
rethinkdb-2.4.9.dist-info/WHEEL
rethinkdb-2.4.9.dist-info/entry_points.txt
rethinkdb-2.4.9.dist-info/top_level.txt
rethinkdb-2.4.9.dist-info/zip-safe
rethinkdb-2.4.9.dist-info/RECORD
