Metadata-Version: 2.1
Name: rethinkdb
Version: 2.4.9
Summary: Python driver library for the RethinkDB database server.
Home-page: https://github.com/RethinkDB/rethinkdb-python
Maintainer: RethinkDB.
Maintainer-email: bugs@rethinkdb.com
Classifier: Intended Audience :: Developers
Classifier: Natural Language :: English
Classifier: Programming Language :: Python :: 2
Classifier: Programming Language :: Python :: 2.7
Classifier: Programming Language :: Python :: 3
Classifier: Programming Language :: Python :: 3.5
Classifier: Programming Language :: Python :: 3.6
Classifier: Programming Language :: Python :: 3.7
Classifier: Programming Language :: Python :: 3.8
Requires-Python: >=2.7, !=3.0.*, !=3.1.*, !=3.2.*, !=3.3.*
License-File: LICENSE
